ShentouCeshiShizhanDisanbanHongduiBan/README.md
ShentouCeshiShizhanDisanbanHongduiBan/__init__.py
ShentouCeshiShizhanDisanbanHongduiBan/__main__.py
ShentouCeshiShizhanDisanbanHongduiBan/file.epub
ShentouCeshiShizhanDisanbanHongduiBan/index.html
ShentouCeshiShizhanDisanbanHongduiBan/css/__init__.py
ShentouCeshiShizhanDisanbanHongduiBan/css/annotations.css
ShentouCeshiShizhanDisanbanHongduiBan/css/main.css
ShentouCeshiShizhanDisanbanHongduiBan/css/normalize.css
ShentouCeshiShizhanDisanbanHongduiBan/css/popup.css
ShentouCeshiShizhanDisanbanHongduiBan/font/__init__.py
ShentouCeshiShizhanDisanbanHongduiBan/font/fontello.eot
ShentouCeshiShizhanDisanbanHongduiBan/font/fontello.svg
ShentouCeshiShizhanDisanbanHongduiBan/font/fontello.ttf
ShentouCeshiShizhanDisanbanHongduiBan/font/fontello.woff
ShentouCeshiShizhanDisanbanHongduiBan/img/__init__.py
ShentouCeshiShizhanDisanbanHongduiBan/img/annotator-glyph-sprite.png
ShentouCeshiShizhanDisanbanHongduiBan/img/annotator-icon-sprite.png
ShentouCeshiShizhanDisanbanHongduiBan/img/apple-touch-icon.png
ShentouCeshiShizhanDisanbanHongduiBan/img/cancelfullscreen.png
ShentouCeshiShizhanDisanbanHongduiBan/img/close.png
ShentouCeshiShizhanDisanbanHongduiBan/img/fullscreen.png
ShentouCeshiShizhanDisanbanHongduiBan/img/loader.gif
ShentouCeshiShizhanDisanbanHongduiBan/img/menu-icon.png
ShentouCeshiShizhanDisanbanHongduiBan/img/save.png
ShentouCeshiShizhanDisanbanHongduiBan/img/saved.png
ShentouCeshiShizhanDisanbanHongduiBan/img/settings-s.png
ShentouCeshiShizhanDisanbanHongduiBan/img/settings.png
ShentouCeshiShizhanDisanbanHongduiBan/img/star.png
ShentouCeshiShizhanDisanbanHongduiBan/js/__init__.py
ShentouCeshiShizhanDisanbanHongduiBan/js/epub.js
ShentouCeshiShizhanDisanbanHongduiBan/js/epub.min.js
ShentouCeshiShizhanDisanbanHongduiBan/js/epub.min.map
ShentouCeshiShizhanDisanbanHongduiBan/js/hooks.min.js
ShentouCeshiShizhanDisanbanHongduiBan/js/hooks.min.map
ShentouCeshiShizhanDisanbanHongduiBan/js/reader.js
shentou_ceshi_shizhan_disanban_hongdui_ban-2024.3.5.0.dist-info/METADATA
shentou_ceshi_shizhan_disanban_hongdui_ban-2024.3.5.0.dist-info/WHEEL
shentou_ceshi_shizhan_disanban_hongdui_ban-2024.3.5.0.dist-info/entry_points.txt
shentou_ceshi_shizhan_disanban_hongdui_ban-2024.3.5.0.dist-info/top_level.txt
shentou_ceshi_shizhan_disanban_hongdui_ban-2024.3.5.0.dist-info/RECORD
